{
  "main": {
    "id": "468fe14b7016391c",
    "type": "split",
    "children": [
      {
        "id": "48ff3a044cc005d9",
        "type": "split",
        "children": [
          {
            "id": "b2583826bd0c8f9a",
            "type": "tabs",
            "dimension": 82.96422487223168,
            "children": [
              {
                "id": "d261942955f0c304",
                "type": "leaf",
                "state": {
                  "type": "markdown",
                  "state": {
                    "file": "Secondo Anno/Algebra Lineare/exercise/Esercizi Svolti.md",
                    "mode": "source",
                    "source": false
                  }
                }
              },
              {
                "id": "8c800d8153e396b4",
                "type": "leaf",
                "state": {
                  "type": "markdown",
                  "state": {
                    "file": "Secondo Anno/cheatsheet_lat/cheatsheet.md",
                    "mode": "preview",
                    "source": false
                  }
                }
              }
            ]
          },
          {
            "id": "c5ba50823fe7acb7",
            "type": "tabs",
            "dimension": 17.035775127768314,
            "children": [
              {
                "id": "acd4cefb4ae7d37e",
                "type": "leaf",
                "state": {
                  "type": "pdf",
                  "state": {
                    "file": "Secondo Anno/Algebra Lineare/Lezioni/A-Lezione 1.pdf"
                  }
                }
              },
              {
                "id": "d93ccbfab89012fb",
                "type": "leaf",
                "state": {
                  "type": "pdf",
                  "state": {
                    "file": "Secondo Anno/Algebra Lineare/Tavola funzioni goniometriche-2-3.pdf"
                  }
                }
              },
              {
                "id": "ae5adde9a4076c46",
                "type": "leaf",
                "state": {
                  "type": "pdf",
                  "state": {
                    "file": "Secondo Anno/Algebra Lineare/Algebra Lineare appunti_annotated.pdf"
                  }
                }
              },
              {
                "id": "896377b3cc1a29e1",
                "type": "leaf",
                "state": {
                  "type": "pdf",
                  "state": {
                    "file": "Secondo Anno/Algebra Lineare/Lezioni/Lezione 5.pdf"
                  }
                }
              },
              {
                "id": "47c4eee4238a84a3",
                "type": "leaf",
                "state": {
                  "type": "pdf",
                  "state": {
                    "file": "Secondo Anno/Algebra Lineare/Lezioni/Lezione 15.pdf"
                  }
                }
              },
              {
                "id": "1b0f37db4a820092",
                "type": "leaf",
                "state": {
                  "type": "pdf",
                  "state": {
                    "file": "Secondo Anno/OOP/modulo 2/exercise/Eserciziario.pdf"
                  }
                }
              },
              {
                "id": "6ec6ee689b3fe0b4",
                "type": "leaf",
                "state": {
                  "type": "pdf",
                  "state": {
                    "file": "Secondo Anno/OOP/modulo 2/Effective Java_ Programming Language Guide ( PDFDrive ).pdf"
                  }
                }
              }
            ],
            "currentTab": 5
          }
        ],
        "direction": "horizontal"
      },
      {
        "id": "ee8628f689ff52cd",
        "type": "tabs",
        "children": [
          {
            "id": "dc0071e18e7715d7",
            "type": "leaf",
            "state": {
              "type": "pdf",
              "state": {
                "file": "Secondo Anno/Algebra Lineare/exercise/Foglio2_vettori_sp_vett.pdf"
              }
            }
          },
          {
            "id": "c06f8dc5a06c2a7d",
            "type": "leaf",
            "state": {
              "type": "pdf",
              "state": {
                "file": "Secondo Anno/Algebra Lineare/exercise/20210111 Primo appello - Soluzioni.pdf"
              }
            }
          },
          {
            "id": "5806bd8d5dddc731",
            "type": "leaf",
            "state": {
              "type": "pdf",
              "state": {
                "file": "Secondo Anno/Algebra Lineare/exercise/Simulazione_esame_svolta.pdf"
              }
            }
          },
          {
            "id": "de860c5d05983521",
            "type": "leaf",
            "state": {
              "type": "markdown",
              "state": {
                "file": "Secondo Anno/OOP/modulo 2/exercise/Domande Eserciziario.md",
                "mode": "source",
                "source": false
              }
            }
          }
        ]
      }
    ],
    "direction": "vertical"
  },
  "left": {
    "id": "90aeeda6d98d985d",
    "type": "split",
    "children": [
      {
        "id": "98309e5baaff4f98",
        "type": "tabs",
        "children": [
          {
            "id": "676356614d8bc787",
            "type": "leaf",
            "state": {
              "type": "file-explorer",
              "state": {
                "sortOrder": "alphabetical"
              }
            }
          },
          {
            "id": "dd3f5587c8fdd0fd",
            "type": "leaf",
            "state": {
              "type": "search",
              "state": {
                "query": "",
                "matchingCase": false,
                "explainSearch": false,
                "collapseAll": false,
                "extraContext": false,
                "sortOrder": "alphabetical"
              }
            }
          },
          {
            "id": "313a11dd7bf807e6",
            "type": "leaf",
            "state": {
              "type": "bookmarks",
              "state": {}
            }
          }
        ]
      }
    ],
    "direction": "horizontal",
    "width": 695.0110321044922,
    "collapsed": true
  },
  "right": {
    "id": "9cf4d1525f8d4e32",
    "type": "split",
    "children": [
      {
        "id": "6c89e6687f0b156f",
        "type": "tabs",
        "children": [
          {
            "id": "41dc71b730dfb0f2",
            "type": "leaf",
            "state": {
              "type": "backlink",
              "state": {
                "file": "Secondo Anno/Algebra Lineare/exercise/Esercizi Svolti.md",
                "collapseAll": false,
                "extraContext": false,
                "sortOrder": "alphabetical",
                "showSearch": false,
                "searchQuery": "",
                "backlinkCollapsed": false,
                "unlinkedCollapsed": true
              }
            }
          },
          {
            "id": "7f37a21e6f59afb2",
            "type": "leaf",
            "state": {
              "type": "outgoing-link",
              "state": {
                "file": "Secondo Anno/Algebra Lineare/exercise/Esercizi Svolti.md",
                "linksCollapsed": false,
                "unlinkedCollapsed": true
              }
            }
          },
          {
            "id": "881b68a7f9267ff0",
            "type": "leaf",
            "state": {
              "type": "tag",
              "state": {
                "sortOrder": "frequency",
                "useHierarchy": true
              }
            }
          },
          {
            "id": "c1bc1ec7a4c3b947",
            "type": "leaf",
            "state": {
              "type": "outline",
              "state": {
                "file": "Secondo Anno/Algebra Lineare/exercise/Esercizi Svolti.md"
              }
            }
          }
        ],
        "currentTab": 3
      }
    ],
    "direction": "horizontal",
    "width": 300,
    "collapsed": true
  },
  "left-ribbon": {
    "hiddenItems": {
      "switcher:Open quick switcher": false,
      "graph:Open graph view": false,
      "canvas:Create new canvas": false,
      "daily-notes:Open today's daily note": false,
      "templates:Insert template": false,
      "command-palette:Open command palette": false
    }
  },
  "active": "d261942955f0c304",
  "lastOpenFiles": [
    "Secondo Anno/Algebra Lineare/exercise/Foglio2_vettori_sp_vett.pdf",
    "Secondo Anno/Algebra Lineare/exercise/Numeri Complessi.pdf",
    "Secondo Anno/Algebra Lineare/exercise/20210111 Primo appello - Soluzioni.pdf",
    "Secondo Anno/Algebra Lineare/exercise/Esercizi Svolti.md",
    "Secondo Anno/Algebra Lineare/exercise/Simulazione_esame_svolta.pdf",
    "Secondo Anno/OOP/modulo 2/exercise/Domande Eserciziario.md",
    "Secondo Anno/OOP/modulo 2/exercise/theory/Command.md",
    "Secondo Anno/OOP/modulo 2/exercise/Eserciziario.pdf",
    "Pasted image 20240417121913.png",
    "Pasted image 20240417121852.png",
    "Secondo Anno/OOP/modulo 2/exercise/theory/Factory.md",
    "Secondo Anno/OOP/modulo 2/Effective Java_ Programming Language Guide ( PDFDrive ).pdf",
    "Secondo Anno/OOP/modulo 2/exercise/theory/Singleton.md",
    "Secondo Anno/OOP/modulo 2/exercise/theory",
    "Secondo Anno/OOP/modulo 2/exercise/code",
    "Secondo Anno/OOP/modulo 2/exercise/Eserciziario.pdf.crdownload",
    "Secondo Anno/cheatsheet_lat/cheatsheet.md",
    "Secondo Anno/Algebra Lineare/exercise/Foglio7_simul_parz_esame.pdf",
    "Secondo Anno/Algebra Lineare/exercise/Foglio7_simul_parz_esame.pdf.crdownload",
    "Secondo Anno/Basi di dati 2/Trigger.md",
    "Untitled.md",
    "Untitled 1.md",
    "Secondo Anno/Analisi dei dati/esami/Esami passati.md",
    "Secondo Anno/Analisi dei dati/esami/cristiano-varin-ex2.knit.md",
    "Secondo Anno/Analisi dei dati/esami/alberto-campagnolo-ex1.knit.md",
    "Secondo Anno/Analisi dei dati/esami/campagnolo-ex1.knit.md",
    "Secondo Anno/Analisi dei dati/esami/cristiano-varin-ex1.knit.md",
    "Secondo Anno/Analisi dei dati/Analisi di dati.md",
    "Pasted image 20240404175638.png",
    "Pasted image 20240404175600.png",
    "Pasted image 20240404175227.png",
    "Pasted image 20240404175207.png",
    "Secondo Anno/Analisi dei dati/exercise/Esercizi.md",
    "Secondo Anno/Basi di Dati/studio per esame/Test di scrittura del modello concettuale.md",
    "Pasted image 20240402110013.png",
    "Secondo Anno/Sistemi Operativi/modulo 2/Modulo 2.md",
    "Secondo Anno/Basi di dati 2/Sicurezza.md",
    "Pasted image 20240320113029.png",
    "Pasted image 20240320112316.png",
    "Pasted image 20240320112111.png",
    "Secondo Anno/Basi di dati 2/Index.md",
    "Secondo Anno/Sistemi Operativi/modulo 1/3.1-7/utils/Directories.md",
    "Secondo Anno/Sistemi Operativi/modulo 1/3.1-7/Memoria.md",
    "Secondo Anno/Sistemi Operativi/modulo 1/3.1-7/utils/Intro.md",
    "Secondo Anno/Sistemi Operativi/modulo 1/EXAM.md",
    "Secondo Anno/Sistemi Operativi/modulo 1/Indice.md",
    "Untitled.canvas"
  ]
}